bda3/__init__.py
bda3/__version__.py
bda3/models.py
bda3-0.1.0.dist-info/LICENSE
bda3-0.1.0.dist-info/METADATA
bda3-0.1.0.dist-info/WHEEL
bda3-0.1.0.dist-info/top_level.txt
bda3-0.1.0.dist-info/RECORD
