Metadata-Version: 2.1
Name: bda3
Version: 0.1.0
Summary: Algorithms from the book Bayesian Data Analysis by Gelman et. al.
Author: Alexander Dolich
Author-email: alexander.dolich@kit.edu
License: MIT
License-File: LICENSE
